Metadata-Version: 2.1
Name: DNNI
Version: 0.1
Summary: Deep Neural Network Integration(DNNI) - A package to obtain anti-derivatives using Deep Neural Networks
Author: Dibyajyoti Chakraborty
Author-email: dibyajyoti43@gmail.com
License: UNKNOWN
Platform: UNKNOWN
